LICENSE
MANIFEST.in
README.rst
setup.py
django_s3_storage/__init__.py
django_s3_storage/conf.py
django_s3_storage/storage.py
django_s3_storage/tests.py
django_s3_storage/management/__init__.py
django_s3_storage/management/commands/__init__.py
django_s3_storage/management/commands/s3_sync_meta.py
django_s3_storage_patched.egg-info/PKG-INFO
django_s3_storage_patched.egg-info/SOURCES.txt
django_s3_storage_patched.egg-info/dependency_links.txt
django_s3_storage_patched.egg-info/requires.txt
django_s3_storage_patched.egg-info/top_level.txt