Metadata-Version: 1.1
Name: django-s3-storage-patched
Version: 0.9.6.2
Summary: Django Amazon S3 file storage.
Home-page: https://github.com/etianen/django-s3-storage
Author: Dave Hall
Author-email: dave@etianen.com
License: BSD
Platform: UNKNOWN
Classifier: Development Status :: 4 - Beta
Classifier: Environment :: Web Environment
Classifier: Intended Audience :: Developers
Classifier: License :: OSI Approved :: BSD License
Classifier: Operating System :: OS Independent
Classifier: Programming Language :: Python
Classifier: Programming Language :: Python :: 2.7
Classifier: Programming Language :: Python :: 3.3
Classifier: Programming Language :: Python :: 3.4
Classifier: Framework :: Django
